ddsp/__init__.py
ddsp/core.py
ddsp/core_test.py
ddsp/dags.py
ddsp/dags_test.py
ddsp/effects.py
ddsp/effects_test.py
ddsp/losses.py
ddsp/losses_test.py
ddsp/processors.py
ddsp/processors_test.py
ddsp/spectral_ops.py
ddsp/spectral_ops_test.py
ddsp/synths.py
ddsp/synths_test.py
ddsp/test_util.py
ddsp/version.py
ddsp/colab/__init__.py
ddsp/colab/colab_utils.py
ddsp/training/__init__.py
ddsp/training/cloud.py
ddsp/training/cloud_test.py
ddsp/training/data.py
ddsp/training/ddsp_export.py
ddsp/training/ddsp_run.py
ddsp/training/decoders.py
ddsp/training/decoders_test.py
ddsp/training/encoders.py
ddsp/training/eval_util.py
ddsp/training/evaluators.py
ddsp/training/heuristics.py
ddsp/training/heuristics_test.py
ddsp/training/inference.py
ddsp/training/metrics.py
ddsp/training/metrics_test.py
ddsp/training/nn.py
ddsp/training/nn_test.py
ddsp/training/plotting.py
ddsp/training/postprocessing.py
ddsp/training/preprocessing.py
ddsp/training/preprocessing_test.py
ddsp/training/summaries.py
ddsp/training/train_util.py
ddsp/training/trainers.py
ddsp/training/data_preparation/__init__.py
ddsp/training/data_preparation/ddsp_generate_synthetic_dataset.py
ddsp/training/data_preparation/ddsp_prepare_tfrecord.py
ddsp/training/data_preparation/prepare_tfrecord_lib.py
ddsp/training/data_preparation/prepare_tfrecord_lib_test.py
ddsp/training/data_preparation/synthetic_data.py
ddsp/training/docker/__init__.py
ddsp/training/docker/ddsp_ai_platform.py
ddsp/training/docker/task.py
ddsp/training/docker/task_test.py
ddsp/training/gin/__init__.py
ddsp/training/gin/datasets/__init__.py
ddsp/training/gin/datasets/base.gin
ddsp/training/gin/datasets/nsynth.gin
ddsp/training/gin/datasets/tfrecord.gin
ddsp/training/gin/eval/__init__.py
ddsp/training/gin/eval/basic.gin
ddsp/training/gin/eval/basic_f0_ld.gin
ddsp/training/gin/eval/basic_f0_ld_twm.gin
ddsp/training/gin/eval/heuristic.gin
ddsp/training/gin/eval/heuristic_power.gin
ddsp/training/gin/eval/midi_ae.gin
ddsp/training/gin/models/__init__.py
ddsp-3.7.0.dist-info/LICENSE
ddsp-3.7.0.dist-info/METADATA
ddsp-3.7.0.dist-info/WHEEL
ddsp-3.7.0.dist-info/entry_points.txt
ddsp-3.7.0.dist-info/top_level.txt
ddsp-3.7.0.dist-info/RECORD
